time_pattern_cohesion_score/__init__.py
time_pattern_cohesion_score/time_pattern_cohesion_score.py
tpcs-0.0.5.dist-info/LICENSE
tpcs-0.0.5.dist-info/METADATA
tpcs-0.0.5.dist-info/WHEEL
tpcs-0.0.5.dist-info/top_level.txt
tpcs-0.0.5.dist-info/RECORD
