Metadata-Version: 2.1
Name: tpcs
Version: 0.0.5
Summary: TPCS is a metric to assess how well time-dependent patterns within a time series signal remain connected over time, with an emphasis on recency.
Home-page: https://github.com/karaposu/time-pattern-cohesion-score
Author: Enes
Author-email: enesesvetkuzucu@gmail.com
Project-URL: Bug Tracker, https://github.com/karaposu/time-pattern-cohesion-score/issues
Classifier: Programming Language :: Python :: 3
Classifier: License :: OSI Approved :: MIT License
Classifier: Operating System :: OS Independent
Requires-Python: >=3.6
License-File: LICENSE
Requires-Dist: numpy >=1.15.0
Requires-Dist: pandas >=1.15.0
Requires-Dist: sequentiality
